<annotation>
	<folder></folder>
	<filename>raccoon-187_jpg.rf.2ysvpJGjHEw8f8FN5dwY.jpg</filename>
	<path>raccoon-187_jpg.rf.2ysvpJGjHEw8f8FN5dwY.jpg</path>
	<source>
		<database>roboflow.ai</database>
	</source>
	<size>
		<width>362</width>
		<height>357</height>
		<depth>3</depth>
	</size>
	<segmented>0</segmented>
	<object>
		<name>raccoon</name>
		<pose>Unspecified</pose>
		<truncated>0</truncated>
		<difficult>0</difficult>
		<occluded>0</occluded>
		<bndbox>
			<xmin>162</xmin>
			<xmax>293</xmax>
			<ymin>113</ymin>
			<ymax>277</ymax>
		</bndbox>
	</object>
</annotation>
