<annotation>
	<folder></folder>
	<filename>raccoon-158_jpg.rf.CaIznH9vPpPMK6nK2nvV.jpg</filename>
	<path>raccoon-158_jpg.rf.CaIznH9vPpPMK6nK2nvV.jpg</path>
	<source>
		<database>roboflow.ai</database>
	</source>
	<size>
		<width>275</width>
		<height>183</height>
		<depth>3</depth>
	</size>
	<segmented>0</segmented>
	<object>
		<name>raccoon</name>
		<pose>Unspecified</pose>
		<truncated>0</truncated>
		<difficult>0</difficult>
		<occluded>0</occluded>
		<bndbox>
			<xmin>24</xmin>
			<xmax>263</xmax>
			<ymin>24</ymin>
			<ymax>178</ymax>
		</bndbox>
	</object>
</annotation>
